setup.py
alisms/__init__.py
alisms/utils.py
alisms.egg-info/PKG-INFO
alisms.egg-info/SOURCES.txt
alisms.egg-info/dependency_links.txt
alisms.egg-info/requires.txt
alisms.egg-info/top_level.txt