Metadata-Version: 1.2
Name: alisms
Version: 1.1.0
Summary: A SDK for Aliyun SMS services in Python3
Home-page: https://github.com/houluy/Aliyun-SMS
Author: Houlu
Author-email: houlu8674@bupt.edu.cn
License: MIT
Keywords: Aliyun SMS SDK
Platform: UNKNOWN
Classifier: Development Status :: 5 - Production/Stable
Classifier: Intended Audience :: Developers
Classifier: Topic :: Software Development :: Libraries :: Python Modules
Classifier: Programming Language :: Python :: 3
Classifier: Programming Language :: Python :: 3.3
Classifier: Programming Language :: Python :: 3.4
Classifier: Programming Language :: Python :: 3.5
Classifier: Programming Language :: Python :: 3.6
Requires-Python: >=3
